perceptive_crop_image/__init__.py
perceptive_crop_image/crop.py
perceptive_crop_image-2.0.0.dist-info/LICENSE
perceptive_crop_image-2.0.0.dist-info/METADATA
perceptive_crop_image-2.0.0.dist-info/WHEEL
perceptive_crop_image-2.0.0.dist-info/top_level.txt
perceptive_crop_image-2.0.0.dist-info/RECORD
