Metadata-Version: 2.1
Name: perceptive_crop_image
Version: 2.0.0
Summary: A manual cropping tool using OpenCV.
Home-page: https://github.com/fathimaCode
Author: Fathima
Author-email: fathima.offical.msg@gmail.com
Classifier: Programming Language :: Python :: 3
Classifier: License :: OSI Approved :: MIT License
Classifier: Operating System :: OS Independent
License-File: LICENSE
Requires-Dist: numpy
Requires-Dist: opencv-python
